[
  {
    "id":"",
    "privilegeName":"用户",
    "alias":"用户",
    "privilegeUri":"/management/user",
    "privilegeMethod":"GET",
    "icon":"",
    "seq":0,
    "level":1,
    "ref":""
  }
,{
  "id":"",
  "privilegeName":"添加用户",
  "alias":"添加用户",
  "privilegeUri":"/management/user/register",
  "privilegeMethod":"GET",
  "icon":"",
  "seq":0,
  "level":2,
  "ref":"用户"
}
,{
  "id":"",
  "privilegeName":"删除用户",
  "alias":"删除用户",
  "privilegeUri":"/management/user/delUser",
  "privilegeMethod":"POST",
  "icon":"",
  "seq":0,
  "level":2,
  "ref":"用户"
}
,{
  "id":"",
  "privilegeName":"查看用户信息",
  "alias":"查看用户信息",
  "privilegeUri":"/management/user/detilsModal",
  "privilegeMethod":"GET",
  "icon":"",
  "seq":0,
  "level":2,
  "ref":"用户"
}
,{
  "id":"",
  "privilegeName":"用户列表",
  "alias":"用户列表",
  "privilegeUri":"/management/user/listUser",
  "privilegeMethod":"GET",
  "icon":"",
  "seq":0,
  "level":2,
  "ref":"用户"
}
,{
  "id":"",
  "privilegeName":"查看用户列表",
  "alias":"查看用户列表",
  "privilegeUri":"/management/user/listUser",
  "privilegeMethod":"POST",
  "icon":"",
  "seq":0,
  "level":2,
  "ref":"用户"
}
,{
  "id":"",
  "privilegeName":"修改用户信息",
  "alias":"修改用户信息",
  "privilegeUri":"/management/user/updateUser",
  "privilegeMethod":"POST",
  "icon":"",
  "seq":0,
  "level":2,
  "ref":"用户"
}
,{
  "id":"",
  "privilegeName":"修改个人信息",
  "alias":"修改个人信息",
  "privilegeUri":"/management/user/updateMy",
  "privilegeMethod":"POST",
  "icon":"",
  "seq":0,
  "level":2,
  "ref":"用户"
}
,{
  "id":"",
  "privilegeName":"修改用户权限",
  "alias":"修改用户权限",
  "privilegeUri":"/management/user/userRoleEditModal",
  "privilegeMethod":"GET",
  "icon":"",
  "seq":0,
  "level":2,
  "ref":"用户"
}
,{
  "id":"",
  "privilegeName":"角色",
  "alias":"角色",
  "privilegeUri":"/management/role",
  "privilegeMethod":"GET",
  "icon":"",
  "seq":0,
  "level":1,
  "ref":""
}
,{
  "id":"",
  "privilegeName":"角色列表",
  "alias":"角色列表",
  "privilegeUri":"/management/role/listRole",
  "privilegeMethod":"GET",
  "icon":"",
  "seq":0,
  "level":2,
  "ref":"角色"
}
,{
  "id":"",
  "privilegeName":"查看角色列表",
  "alias":"查看角色列表",
  "privilegeUri":"/management/role/listRole",
  "privilegeMethod":"POST",
  "icon":"",
  "seq":0,
  "level":2,
  "ref":"角色"
}
,{
  "id":"",
  "privilegeName":"查看角色详情",
  "alias":"查看角色详情",
  "privilegeUri":"/management/role/roleDetils",
  "privilegeMethod":"GET",
  "icon":"",
  "seq":0,
  "level":2,
  "ref":"角色"
}
,{
  "id":"",
  "privilegeName":"添加角色",
  "alias":"添加角色",
  "privilegeUri":"/management/role/addRole",
  "privilegeMethod":"GET",
  "icon":"",
  "seq":0,
  "level":2,
  "ref":"角色"
}
,{
  "id":"",
  "privilegeName":"删除角色",
  "alias":"删除角色",
  "privilegeUri":"/management/role/delRole",
  "privilegeMethod":"GET",
  "icon":"",
  "seq":0,
  "level":2,
  "ref":"角色"
}
,{
  "id":"",
  "privilegeName":"更新角色",
  "alias":"更新角色",
  "privilegeUri":"/management/role/updateRole",
  "privilegeMethod":"POST",
  "icon":"",
  "seq":0,
  "level":2,
  "ref":"角色"
}
,{
  "id":"",
  "privilegeName":"角色权限分配",
  "alias":"角色权限分配",
  "privilegeUri":"/management/role/rolePrivilegeEditModal",
  "privilegeMethod":"GET",
  "icon":"",
  "seq":0,
  "level":2,
  "ref":"角色"
}
,{
  "id":"",
  "privilegeName":"用户角色分配",
  "alias":"用户角色分配",
  "privilegeUri":"/management/role/authUser",
  "privilegeMethod":"POST",
  "icon":"",
  "seq":0,
  "level":2,
  "ref":"角色"
}
,{
  "id":"",
  "privilegeName":"权限",
  "alias":"权限",
  "privilegeUri":"/management/privilege",
  "privilegeMethod":"GET",
  "icon":"",
  "seq":0,
  "level":1,
  "ref":""
}
,{
  "id":"",
  "privilegeName":"权限列表",
  "alias":"权限列表",
  "privilegeUri":"/management/privilege/listPrivilege",
  "privilegeMethod":"GET",
  "icon":"",
  "seq":0,
  "level":2,
  "ref":"权限"
}
,{
  "id":"",
  "privilegeName":"查看权限列表",
  "alias":"查看权限列表",
  "privilegeUri":"/management/privilege/listPrivilege",
  "privilegeMethod":"POST",
  "icon":"",
  "seq":0,
  "level":2,
  "ref":"权限"
}
,{
  "id":"",
  "privilegeName":"查看权限详情",
  "alias":"查看权限详情",
  "privilegeUri":"/management/privilege/privilegeDetils",
  "privilegeMethod":"GET",
  "icon":"",
  "seq":0,
  "level":2,
  "ref":"权限"
}
,{
  "id":"",
  "privilegeName":"新建权限",
  "alias":"新建权限",
  "privilegeUri":"/management/privilege/addPrivilege",
  "privilegeMethod":"POST",
  "icon":"",
  "seq":0,
  "level":2,
  "ref":"权限"
}
,{
  "id":"",
  "privilegeName":"删除权限",
  "alias":"删除权限",
  "privilegeUri":"/management/privilege/delPrivilege",
  "privilegeMethod":"GET",
  "icon":"",
  "seq":0,
  "level":2,
  "ref":"权限"
}
,{
  "id":"",
  "privilegeName":"更新权限",
  "alias":"更新权限",
  "privilegeUri":"/management/privilege/updatePrivilege",
  "privilegeMethod":"POST",
  "icon":"",
  "seq":0,
  "level":2,
  "ref":"权限"
},
  {
    "id":"",
    "privilegeName":"用户",
    "alias":"用户",
    "privilegeUri":"/management/user",
    "privilegeMethod":"GET",
    "icon":"",
    "seq":0,
    "level":1,
    "ref":""
  }
]
